morse_audio_decoder/__init__.py
morse_audio_decoder/__main__.py
morse_audio_decoder/io.py
morse_audio_decoder/morse.ini
morse_audio_decoder/morse.py
morse_audio_decoder/processing.py
morse_audio_decoder-0.1.0.dist-info/entry_points.txt
morse_audio_decoder-0.1.0.dist-info/LICENSE
morse_audio_decoder-0.1.0.dist-info/WHEEL
morse_audio_decoder-0.1.0.dist-info/METADATA
morse_audio_decoder-0.1.0.dist-info/RECORD
